CHANGES.md
LICENSE
MANIFEST.in
README.md
setup.cfg
setup.py
skal/__init__.py
skal/core.py
skal/version.py
skal.egg-info/PKG-INFO
skal.egg-info/SOURCES.txt
skal.egg-info/dependency_links.txt
skal.egg-info/top_level.txt